{
  "GlottoCode": "dupa1235",
  "LanguageName": "Dupaningan Agta; Eastern Cagayan Agta; Dupaninan Agta",
  "ISO6393": "duo",
  "SpecificDialect": "NA",
  "phones": {
    "0062": {
      "glyph": "b",
      "allophones": "NA"
    },
    "0064": {
      "glyph": "d",
      "allophones": "NA"
    },
    "0068": {
      "glyph": "h",
      "allophones": "h"
    },
    "006A": {
      "glyph": "j",
      "allophones": "NA"
    },
    "006B": {
      "glyph": "k",
      "allophones": "NA"
    },
    "006C": {
      "glyph": "l",
      "allophones": "NA"
    },
    "006D": {
      "glyph": "m",
      "allophones": "NA"
    },
    "0070": {
      "glyph": "p",
      "allophones": "NA"
    },
    "0073": {
      "glyph": "s",
      "allophones": "NA"
    },
    "0074": {
      "glyph": "t",
      "allophones": "NA"
    },
    "0077": {
      "glyph": "w",
      "allophones": "NA"
    },
    "014B": {
      "glyph": "\u014b",
      "allophones": "NA"
    },
    "0261": {
      "glyph": "\u0261",
      "allophones": "NA"
    },
    "027E": {
      "glyph": "\u027e",
      "allophones": "\u027e r"
    },
    "0294": {
      "glyph": "\u0294",
      "allophones": "NA"
    },
    "0061": {
      "glyph": "a",
      "allophones": "a"
    },
    "0069": {
      "glyph": "i",
      "allophones": "NA"
    },
    "006F": {
      "glyph": "o",
      "allophones": "NA"
    },
    "0075": {
      "glyph": "u",
      "allophones": "NA"
    },
    "025B": {
      "glyph": "\u025b",
      "allophones": "NA"
    },
    "006E": {
      "glyph": "n",
      "allophones": "NA"
    },
    "0072": {
      "glyph": "r",
      "allophones": "NA"
    },
    "0061+0308": {
      "glyph": "a\u0308",
      "allophones": "NA"
    },
    "0259": {
      "glyph": "\u0259",
      "allophones": "NA"
    }
  },
  "ComplexPhoneList": "a a\u0308 b d h i j k l m n o p r s t u w \u014b \u0259 \u025b \u0261 \u027e \u0294",
  "ComponentList": "a a\u0308 b d h i j k l m n o p r s t u w \u014b \u0259 \u025b \u0261 \u027e \u0294"
}