{
  "GlottoCode": "efut1241",
  "LanguageName": "Efutu",
  "ISO6393": "afu",
  "SpecificDialect": "NA",
  "phones": {
    "0062": {
      "glyph": "b",
      "allophones": "b"
    },
    "0064": {
      "glyph": "d",
      "allophones": "d"
    },
    "0064+0291": {
      "glyph": "d\u0291",
      "allophones": "d\u0291"
    },
    "0066": {
      "glyph": "f",
      "allophones": "f"
    },
    "0068": {
      "glyph": "h",
      "allophones": "h"
    },
    "006A": {
      "glyph": "j",
      "allophones": "j"
    },
    "006B": {
      "glyph": "k",
      "allophones": "k"
    },
    "006C": {
      "glyph": "l",
      "allophones": "l"
    },
    "006D": {
      "glyph": "m",
      "allophones": "m"
    },
    "006E": {
      "glyph": "n",
      "allophones": "n"
    },
    "0070": {
      "glyph": "p",
      "allophones": "p"
    },
    "0072": {
      "glyph": "r",
      "allophones": "r"
    },
    "0073": {
      "glyph": "s",
      "allophones": "s"
    },
    "0074": {
      "glyph": "t",
      "allophones": "t"
    },
    "0074+0073": {
      "glyph": "ts",
      "allophones": "ts"
    },
    "0074+0255": {
      "glyph": "t\u0255",
      "allophones": "t\u0255"
    },
    "0077": {
      "glyph": "w",
      "allophones": "w"
    },
    "014B": {
      "glyph": "\u014b",
      "allophones": "\u014b"
    },
    "014B+02B7": {
      "glyph": "\u014b\u02b7",
      "allophones": "\u014b\u02b7"
    },
    "0255": {
      "glyph": "\u0255",
      "allophones": "\u0255"
    },
    "0261": {
      "glyph": "\u0261",
      "allophones": "\u0261"
    },
    "0265": {
      "glyph": "\u0265",
      "allophones": "\u0265"
    },
    "0271": {
      "glyph": "\u0271",
      "allophones": "\u0271"
    },
    "0272": {
      "glyph": "\u0272",
      "allophones": "\u0272"
    },
    "0291": {
      "glyph": "\u0291",
      "allophones": "\u0291"
    },
    "0294": {
      "glyph": "\u0294",
      "allophones": "\u0294"
    },
    "02E6": {
      "glyph": "\u02e6",
      "allophones": "\u02e6"
    },
    "02E8": {
      "glyph": "\u02e8",
      "allophones": "\u02e8"
    },
    "0065": {
      "glyph": "e",
      "allophones": "e"
    },
    "0065+0303": {
      "glyph": "e\u0303",
      "allophones": "e\u0303"
    },
    "0069": {
      "glyph": "i",
      "allophones": "i"
    },
    "0069+0303": {
      "glyph": "i\u0303",
      "allophones": "i\u0303"
    },
    "006F": {
      "glyph": "o",
      "allophones": "o"
    },
    "006F+0303": {
      "glyph": "o\u0303",
      "allophones": "o\u0303"
    },
    "0075": {
      "glyph": "u",
      "allophones": "u"
    },
    "0075+0303": {
      "glyph": "u\u0303",
      "allophones": "u\u0303"
    },
    "0251": {
      "glyph": "\u0251",
      "allophones": "\u0251 a \u00e6 \u0259"
    },
    "0251+0303": {
      "glyph": "\u0251\u0303",
      "allophones": "\u0251\u0303 a\u0303 \u00e6\u0303 \u0259\u0303"
    },
    "0254": {
      "glyph": "\u0254",
      "allophones": "\u0254"
    },
    "0254+0303": {
      "glyph": "\u0254\u0303",
      "allophones": "\u0254\u0303"
    },
    "025B": {
      "glyph": "\u025b",
      "allophones": "\u025b"
    },
    "025B+0303": {
      "glyph": "\u025b\u0303",
      "allophones": "\u025b\u0303"
    },
    "026A": {
      "glyph": "\u026a",
      "allophones": "\u026a"
    },
    "026A+0303": {
      "glyph": "\u026a\u0303",
      "allophones": "\u026a\u0303"
    },
    "028A": {
      "glyph": "\u028a",
      "allophones": "\u028a"
    },
    "028A+0303": {
      "glyph": "\u028a\u0303",
      "allophones": "\u028a\u0303"
    }
  },
  "ComplexPhoneList": "b d d\u0291 e e\u0303 f h i i\u0303 j k l m n o o\u0303 p r s t ts t\u0255 u u\u0303 w \u014b \u014b\u02b7 \u0251 \u0251\u0303 \u0254 \u0254\u0303 \u0255 \u025b \u025b\u0303 \u0261 \u0265 \u026a \u026a\u0303 \u0271 \u0272 \u028a \u028a\u0303 \u0291 \u0294 \u02e6 \u02e8",
  "ComponentList": "b d e e\u0303 f h i i\u0303 j k l m n o o\u0303 p r s t u u\u0303 w \u014b \u014b\u02b7 \u0251 \u0251\u0303 \u0254 \u0254\u0303 \u0255 \u025b \u025b\u0303 \u0261 \u0265 \u026a \u026a\u0303 \u0271 \u0272 \u028a \u028a\u0303 \u0291 \u0294 \u02e6 \u02e8"
}