{
  "GlottoCode": "gras1249",
  "LanguageName": "KOIARI",
  "ISO6393": "kbk",
  "SpecificDialect": "NA",
  "phones": {
    "0062": {
      "glyph": "b",
      "allophones": "NA"
    },
    "0064": {
      "glyph": "d",
      "allophones": "NA"
    },
    "0066": {
      "glyph": "f",
      "allophones": "NA"
    },
    "0068": {
      "glyph": "h",
      "allophones": "NA"
    },
    "006B": {
      "glyph": "k",
      "allophones": "NA"
    },
    "006D": {
      "glyph": "m",
      "allophones": "NA"
    },
    "006E": {
      "glyph": "n",
      "allophones": "NA"
    },
    "0074": {
      "glyph": "t",
      "allophones": "NA"
    },
    "00F0": {
      "glyph": "\u00f0",
      "allophones": "NA"
    },
    "0261": {
      "glyph": "\u0261",
      "allophones": "NA"
    },
    "027E": {
      "glyph": "\u027e",
      "allophones": "NA"
    },
    "0061": {
      "glyph": "a",
      "allophones": "NA"
    },
    "0065+031E": {
      "glyph": "e\u031e",
      "allophones": "NA"
    },
    "0069": {
      "glyph": "i",
      "allophones": "NA"
    },
    "006F+031E": {
      "glyph": "o\u031e",
      "allophones": "NA"
    },
    "0075": {
      "glyph": "u",
      "allophones": "NA"
    }
  },
  "ComplexPhoneList": "a b d e\u031e f h i k m n o\u031e t u \u00f0 \u0261 \u027e",
  "ComponentList": "a b d e\u031e f h i k m n o\u031e t u \u00f0 \u0261 \u027e"
}