{
  "GlottoCode": "kamb1297",
  "LanguageName": "Kikamba",
  "ISO6393": "kam",
  "SpecificDialect": "NA",
  "phones": {
    "006A": {
      "glyph": "j",
      "allophones": "j"
    },
    "006B": {
      "glyph": "k",
      "allophones": "k \u0261 t\u0320\u0283 d\u0320\u0292"
    },
    "006C": {
      "glyph": "l",
      "allophones": "l d"
    },
    "006D": {
      "glyph": "m",
      "allophones": "m"
    },
    "006E": {
      "glyph": "n",
      "allophones": "n"
    },
    "0073": {
      "glyph": "s",
      "allophones": "s z"
    },
    "0074": {
      "glyph": "t",
      "allophones": "t d"
    },
    "0077": {
      "glyph": "w",
      "allophones": "w"
    },
    "00F0": {
      "glyph": "\u00f0",
      "allophones": "\u00f0"
    },
    "014B": {
      "glyph": "\u014b",
      "allophones": "\u014b"
    },
    "0265": {
      "glyph": "\u0265",
      "allophones": "\u0265"
    },
    "0272": {
      "glyph": "\u0272",
      "allophones": "\u0272"
    },
    "03B2": {
      "glyph": "\u03b2",
      "allophones": "\u03b2 b"
    },
    "02E5": {
      "glyph": "\u02e5",
      "allophones": "\u02e5"
    },
    "02E6": {
      "glyph": "\u02e6",
      "allophones": "\u02e6"
    },
    "02E8": {
      "glyph": "\u02e8",
      "allophones": "\u02e8"
    },
    "02E9": {
      "glyph": "\u02e9",
      "allophones": "\u02e9"
    },
    "0061": {
      "glyph": "a",
      "allophones": "a"
    },
    "0061+02D0": {
      "glyph": "a\u02d0",
      "allophones": "a\u02d0"
    },
    "0065": {
      "glyph": "e",
      "allophones": "e"
    },
    "0065+02D0": {
      "glyph": "e\u02d0",
      "allophones": "e\u02d0"
    },
    "0069": {
      "glyph": "i",
      "allophones": "i"
    },
    "0069+02D0": {
      "glyph": "i\u02d0",
      "allophones": "i\u02d0"
    },
    "006F": {
      "glyph": "o",
      "allophones": "o"
    },
    "006F+02D0": {
      "glyph": "o\u02d0",
      "allophones": "o\u02d0"
    },
    "0075": {
      "glyph": "u",
      "allophones": "u"
    },
    "0075+02D0": {
      "glyph": "u\u02d0",
      "allophones": "u\u02d0"
    },
    "0254": {
      "glyph": "\u0254",
      "allophones": "\u0254"
    },
    "0254+02D0": {
      "glyph": "\u0254\u02d0",
      "allophones": "\u0254\u02d0"
    },
    "025B": {
      "glyph": "\u025b",
      "allophones": "\u025b"
    },
    "025B+02D0": {
      "glyph": "\u025b\u02d0",
      "allophones": "\u025b\u02d0"
    }
  },
  "ComplexPhoneList": "a a\u02d0 e e\u02d0 i i\u02d0 j k l m n o o\u02d0 s t u u\u02d0 w \u00f0 \u014b \u0254 \u0254\u02d0 \u025b \u025b\u02d0 \u0265 \u0272 \u02e5 \u02e6 \u02e8 \u02e9 \u03b2",
  "ComponentList": "a a\u02d0 e e\u02d0 i i\u02d0 j k l m n o o\u02d0 s t u u\u02d0 w \u00f0 \u014b \u0254 \u0254\u02d0 \u025b \u025b\u02d0 \u0265 \u0272 \u02e5 \u02e6 \u02e8 \u02e9 \u03b2"
}