{
  "GlottoCode": "saba1268",
  "LanguageName": "Sabane",
  "ISO6393": "sae",
  "SpecificDialect": "NA",
  "phones": {
    "0068": {
      "glyph": "h",
      "allophones": "NA"
    },
    "006A": {
      "glyph": "j",
      "allophones": "j"
    },
    "006B": {
      "glyph": "k",
      "allophones": "NA"
    },
    "006C": {
      "glyph": "l",
      "allophones": "NA"
    },
    "006D": {
      "glyph": "m",
      "allophones": "NA"
    },
    "006E": {
      "glyph": "n",
      "allophones": "NA"
    },
    "0070": {
      "glyph": "p",
      "allophones": "NA"
    },
    "0073": {
      "glyph": "s",
      "allophones": "NA"
    },
    "0074": {
      "glyph": "t",
      "allophones": "NA"
    },
    "0077": {
      "glyph": "w",
      "allophones": "w"
    },
    "0253": {
      "glyph": "\u0253",
      "allophones": "NA"
    },
    "0257": {
      "glyph": "\u0257",
      "allophones": "NA"
    },
    "0294": {
      "glyph": "\u0294",
      "allophones": "NA"
    },
    "0061": {
      "glyph": "a",
      "allophones": "NA"
    },
    "0065": {
      "glyph": "e",
      "allophones": "NA"
    },
    "0069": {
      "glyph": "i",
      "allophones": "NA"
    },
    "006F": {
      "glyph": "o",
      "allophones": "NA"
    },
    "0075": {
      "glyph": "u",
      "allophones": "NA"
    }
  },
  "ComplexPhoneList": "a e h i j k l m n o p s t u w \u0253 \u0257 \u0294",
  "ComponentList": "a e h i j k l m n o p s t u w \u0253 \u0257 \u0294"
}