{
  "GlottoCode": "teen1242",
  "LanguageName": "T\u00e9\u00e9n",
  "ISO6393": "lor",
  "SpecificDialect": "NA",
  "phones": {
    "0062": {
      "glyph": "b",
      "allophones": "b"
    },
    "0063": {
      "glyph": "c",
      "allophones": "c"
    },
    "0064": {
      "glyph": "d",
      "allophones": "d"
    },
    "0066": {
      "glyph": "f",
      "allophones": "f"
    },
    "0068": {
      "glyph": "h",
      "allophones": "h"
    },
    "006A": {
      "glyph": "j",
      "allophones": "j"
    },
    "006A+02E4": {
      "glyph": "j\u02e4",
      "allophones": "j\u02e4"
    },
    "006B": {
      "glyph": "k",
      "allophones": "k"
    },
    "006B+0070": {
      "glyph": "kp",
      "allophones": "kp"
    },
    "006C": {
      "glyph": "l",
      "allophones": "l"
    },
    "006C+02E4": {
      "glyph": "l\u02e4",
      "allophones": "l\u02e4"
    },
    "006D": {
      "glyph": "m",
      "allophones": "m"
    },
    "006E": {
      "glyph": "n",
      "allophones": "n"
    },
    "0070": {
      "glyph": "p",
      "allophones": "p"
    },
    "0070+02E4": {
      "glyph": "p\u02e4",
      "allophones": "p\u02e4"
    },
    "0072": {
      "glyph": "r",
      "allophones": "r"
    },
    "0073": {
      "glyph": "s",
      "allophones": "s"
    },
    "0074": {
      "glyph": "t",
      "allophones": "t"
    },
    "0076": {
      "glyph": "v",
      "allophones": "v"
    },
    "0077": {
      "glyph": "w",
      "allophones": "w"
    },
    "0077+02E4": {
      "glyph": "w\u02e4",
      "allophones": "w\u02e4"
    },
    "0078": {
      "glyph": "x",
      "allophones": "x"
    },
    "007A": {
      "glyph": "z",
      "allophones": "z"
    },
    "014B+006D": {
      "glyph": "\u014bm",
      "allophones": "\u014bm"
    },
    "025F": {
      "glyph": "\u025f",
      "allophones": "\u025f"
    },
    "0261": {
      "glyph": "\u0261",
      "allophones": "\u0261"
    },
    "0261+0062": {
      "glyph": "\u0261b",
      "allophones": "\u0261b"
    },
    "0272": {
      "glyph": "\u0272",
      "allophones": "\u0272"
    },
    "0061": {
      "glyph": "a",
      "allophones": "a"
    },
    "0065": {
      "glyph": "e",
      "allophones": "e"
    },
    "0069": {
      "glyph": "i",
      "allophones": "i"
    },
    "006F": {
      "glyph": "o",
      "allophones": "o"
    },
    "0075": {
      "glyph": "u",
      "allophones": "u"
    },
    "0254": {
      "glyph": "\u0254",
      "allophones": "\u0254"
    },
    "025B": {
      "glyph": "\u025b",
      "allophones": "\u025b"
    },
    "026A": {
      "glyph": "\u026a",
      "allophones": "\u026a"
    },
    "028A": {
      "glyph": "\u028a",
      "allophones": "\u028a"
    },
    "028C": {
      "glyph": "\u028c",
      "allophones": "\u028c"
    }
  },
  "ComplexPhoneList": "a b c d e f h i j j\u02e4 k kp l l\u02e4 m n o p p\u02e4 r s t u v w w\u02e4 x z \u014bm \u0254 \u025b \u025f \u0261 \u0261b \u026a \u0272 \u028a \u028c",
  "ComponentList": "a b c d e f h i j j\u02e4 k l l\u02e4 m n o p p\u02e4 r s t u v w w\u02e4 x z \u014b \u0254 \u025b \u025f \u0261 \u026a \u0272 \u028a \u028c"
}