{
  "GlottoCode": "wayu1241",
  "LanguageName": "Hayu",
  "ISO6393": "vay",
  "SpecificDialect": "NA",
  "phones": {
    "0062": {
      "glyph": "b",
      "allophones": "NA"
    },
    "0064+007A": {
      "glyph": "dz",
      "allophones": "NA"
    },
    "0064+0291": {
      "glyph": "d\u0291",
      "allophones": "NA"
    },
    "0064+032A": {
      "glyph": "d\u032a",
      "allophones": "NA"
    },
    "0068": {
      "glyph": "h",
      "allophones": "NA"
    },
    "006A": {
      "glyph": "j",
      "allophones": "NA"
    },
    "006B": {
      "glyph": "k",
      "allophones": "NA"
    },
    "006B+02B0": {
      "glyph": "k\u02b0",
      "allophones": "NA"
    },
    "006C": {
      "glyph": "l",
      "allophones": "NA"
    },
    "006C+0325": {
      "glyph": "l\u0325",
      "allophones": "NA"
    },
    "006D": {
      "glyph": "m",
      "allophones": "NA"
    },
    "006E+032A": {
      "glyph": "n\u032a",
      "allophones": "NA"
    },
    "0070": {
      "glyph": "p",
      "allophones": "NA"
    },
    "0070+02B0": {
      "glyph": "p\u02b0",
      "allophones": "NA"
    },
    "0073": {
      "glyph": "s",
      "allophones": "NA"
    },
    "0074+0073": {
      "glyph": "ts",
      "allophones": "NA"
    },
    "0074+0073+02B0": {
      "glyph": "ts\u02b0",
      "allophones": "NA"
    },
    "0074+0255": {
      "glyph": "t\u0255",
      "allophones": "NA"
    },
    "0074+032A": {
      "glyph": "t\u032a",
      "allophones": "NA"
    },
    "0074+032A+02B0": {
      "glyph": "t\u032a\u02b0",
      "allophones": "NA"
    },
    "0077": {
      "glyph": "w",
      "allophones": "NA"
    },
    "0078": {
      "glyph": "x",
      "allophones": "NA"
    },
    "014B": {
      "glyph": "\u014b",
      "allophones": "NA"
    },
    "0261": {
      "glyph": "\u0261",
      "allophones": "NA"
    },
    "027E": {
      "glyph": "\u027e",
      "allophones": "NA"
    },
    "028D": {
      "glyph": "\u028d",
      "allophones": "NA"
    },
    "0061": {
      "glyph": "a",
      "allophones": "NA"
    },
    "0061+02D0": {
      "glyph": "a\u02d0",
      "allophones": "NA"
    },
    "0061+0303": {
      "glyph": "a\u0303",
      "allophones": "NA"
    },
    "0061+0303+02D0": {
      "glyph": "a\u0303\u02d0",
      "allophones": "NA"
    },
    "0065": {
      "glyph": "e",
      "allophones": "NA"
    },
    "0065+02D0": {
      "glyph": "e\u02d0",
      "allophones": "NA"
    },
    "0065+0303": {
      "glyph": "e\u0303",
      "allophones": "NA"
    },
    "0065+0303+02D0": {
      "glyph": "e\u0303\u02d0",
      "allophones": "NA"
    },
    "0069": {
      "glyph": "i",
      "allophones": "NA"
    },
    "0069+02D0": {
      "glyph": "i\u02d0",
      "allophones": "NA"
    },
    "0069+0303": {
      "glyph": "i\u0303",
      "allophones": "NA"
    },
    "0069+0303+02D0": {
      "glyph": "i\u0303\u02d0",
      "allophones": "NA"
    },
    "006F": {
      "glyph": "o",
      "allophones": "NA"
    },
    "006F+02D0": {
      "glyph": "o\u02d0",
      "allophones": "NA"
    },
    "006F+0303": {
      "glyph": "o\u0303",
      "allophones": "NA"
    },
    "006F+0303+02D0": {
      "glyph": "o\u0303\u02d0",
      "allophones": "NA"
    },
    "0075": {
      "glyph": "u",
      "allophones": "NA"
    },
    "0075+02D0": {
      "glyph": "u\u02d0",
      "allophones": "NA"
    },
    "0075+0303": {
      "glyph": "u\u0303",
      "allophones": "NA"
    },
    "0075+0303+02D0": {
      "glyph": "u\u0303\u02d0",
      "allophones": "NA"
    },
    "026A": {
      "glyph": "\u026a",
      "allophones": "NA"
    },
    "026A+02D0": {
      "glyph": "\u026a\u02d0",
      "allophones": "NA"
    },
    "026A+0303": {
      "glyph": "\u026a\u0303",
      "allophones": "NA"
    },
    "026A+0303+02D0": {
      "glyph": "\u026a\u0303\u02d0",
      "allophones": "NA"
    },
    "028A": {
      "glyph": "\u028a",
      "allophones": "NA"
    },
    "028A+02D0": {
      "glyph": "\u028a\u02d0",
      "allophones": "NA"
    },
    "028A+0303": {
      "glyph": "\u028a\u0303",
      "allophones": "NA"
    },
    "028A+0303+02D0": {
      "glyph": "\u028a\u0303\u02d0",
      "allophones": "NA"
    }
  },
  "ComplexPhoneList": "a a\u02d0 a\u0303 a\u0303\u02d0 b dz d\u0291 d\u032a e e\u02d0 e\u0303 e\u0303\u02d0 h i i\u02d0 i\u0303 i\u0303\u02d0 j k k\u02b0 l l\u0325 m n\u032a o o\u02d0 o\u0303 o\u0303\u02d0 p p\u02b0 s ts ts\u02b0 t\u0255 t\u032a t\u032a\u02b0 u u\u02d0 u\u0303 u\u0303\u02d0 w x \u014b \u0261 \u026a \u026a\u02d0 \u026a\u0303 \u026a\u0303\u02d0 \u027e \u028a \u028a\u02d0 \u028a\u0303 \u028a\u0303\u02d0 \u028d",
  "ComponentList": "a a\u02d0 a\u0303 a\u0303\u02d0 b d d\u032a e e\u02d0 e\u0303 e\u0303\u02d0 h i i\u02d0 i\u0303 i\u0303\u02d0 j k k\u02b0 l l\u0325 m n\u032a o o\u02d0 o\u0303 o\u0303\u02d0 p p\u02b0 s s\u02b0 t t\u032a t\u032a\u02b0 u u\u02d0 u\u0303 u\u0303\u02d0 w x z \u014b \u0255 \u0261 \u026a \u026a\u02d0 \u026a\u0303 \u026a\u0303\u02d0 \u027e \u028a \u028a\u02d0 \u028a\u0303 \u028a\u0303\u02d0 \u028d \u0291"
}