{
  "GlottoCode": "yuru1263",
  "LanguageName": "Yurut\u00ed",
  "ISO6393": "yui",
  "SpecificDialect": "",
  "phones": {
    "0062": {
      "glyph": "b",
      "allophones": "NA"
    },
    "0064": {
      "glyph": "d",
      "allophones": "NA"
    },
    "0068": {
      "glyph": "h",
      "allophones": "NA"
    },
    "006A": {
      "glyph": "j",
      "allophones": "NA"
    },
    "006B": {
      "glyph": "k",
      "allophones": "NA"
    },
    "0070": {
      "glyph": "p",
      "allophones": "NA"
    },
    "0073": {
      "glyph": "s",
      "allophones": "NA"
    },
    "0074": {
      "glyph": "t",
      "allophones": "NA"
    },
    "0077": {
      "glyph": "w",
      "allophones": "NA"
    },
    "0261": {
      "glyph": "\u0261",
      "allophones": "NA"
    },
    "027E": {
      "glyph": "\u027e",
      "allophones": "NA"
    },
    "0061": {
      "glyph": "a",
      "allophones": "NA"
    },
    "0065": {
      "glyph": "e",
      "allophones": "NA"
    },
    "0069": {
      "glyph": "i",
      "allophones": "NA"
    },
    "006F": {
      "glyph": "o",
      "allophones": "NA"
    },
    "0075": {
      "glyph": "u",
      "allophones": "NA"
    },
    "0268": {
      "glyph": "\u0268",
      "allophones": "NA"
    }
  },
  "ComplexPhoneList": "a b d e h i j k o p s t u w \u0261 \u0268 \u027e",
  "ComponentList": "a b d e h i j k o p s t u w \u0261 \u0268 \u027e"
}